local_keychain_utils/__init__.py
local_keychain_utils/local_keychain_clear.py
local_keychain_utils/local_keychain_get.py
local_keychain_utils/local_keychain_store.py
local_keychain_utils/local_keychain_utils.py
local_keychain_utils-1.0.3.dist-info/METADATA
local_keychain_utils-1.0.3.dist-info/RECORD
local_keychain_utils-1.0.3.dist-info/WHEEL
local_keychain_utils-1.0.3.dist-info/entry_points.txt
local_keychain_utils-1.0.3.dist-info/top_level.txt
