Metadata-Version: 2.1
Name: local-keychain-utils
Version: 1.0.3
Summary: CLI tools to manipulate local keychain
Home-page: https://github.com/apiology/local_keychain_utils
Author: Vince Broz
Author-email: vince@broz.cc
License: MIT license
Keywords: local_keychain_utils
Platform: UNKNOWN
Classifier: Development Status :: 2 - Pre-Alpha
Classifier: Intended Audience :: Developers
Classifier: License :: OSI Approved :: MIT License
Classifier: Natural Language :: English
Classifier: Programming Language :: Python :: 3
Classifier: Programming Language :: Python :: 3.6
Classifier: Programming Language :: Python :: 3.7
Requires-Python: !=2,>=3.6
Requires-Dist: keyring
Requires-Dist: keyrings.alt
Requires-Dist: pycrypto
Requires-Dist: pysectools
